[
  {
    "ID": "ID001",
    "Type": "Percent Change",
    "Units": "",
    "Label": "Percent Change in Total Housing Units",
    "Year": "since 2010"
  },
  {
    "ID": "ID002",
    "Type": "Percent",
    "Units": "",
    "Label": "Percent of Occupied Housing Units, Single Family Owners",
    "Year": 2017
  },
  {
    "ID": "ID003",
    "Type": "Percent Change",
    "Units": "",
    "Label": "Percent Change in Single Family Renters",
    "Year": "since 2010"
  },
  {
    "ID": "ID004",
    "Type": "Percent Change",
    "Units": "",
    "Label": "Percent Change in Single Family Owners",
    "Year": "since 2010"
  },
  {
    "ID": "ID005",
    "Type": "Percent",
    "Units": "",
    "Label": "Percent of Occupied Housing Units, Single Family Renters",
    "Year": 2017
  },
  {
    "ID": "ID006",
    "Type": "Percent Change",
    "Units": "",
    "Label": "Percent Change in Multifamily Units",
    "Year": "since 2010"
  },
  {
    "ID": "ID007",
    "Type": "Job-to-Worker Ratio",
    "Units": "",
    "Label": "Job-to-Worker Ratio",
    "Year": 2017
  },
  {
    "ID": "ID008",
    "Type": "Change",
    "Units": "",
    "Label": "Change in Percent Owner Households",
    "Year": "since 2010"
  },
  {
    "ID": "ID009",
    "Type": "Percent Change",
    "Units": "",
    "Label": "Percent Change in Renter Households",
    "Year": "since 2010"
  },
  {
    "ID": "ID0010",
    "Type": "Percent Change",
    "Units": "",
    "Label": "Percent Change in Owner Households",
    "Year": "since 2010"
  },
  {
    "ID": "ID011",
    "Type": "Change",
    "Units": "",
    "Label": "Change in Single Family Renters",
    "Year": "since 2010"
  },
  {
    "ID": "ID012",
    "Type": "Change",
    "Units": "",
    "Label": "Change in Total Housing Units",
    "Year": "since 2010"
  },
  {
    "ID": "ID013",
    "Type": "Total",
    "Units": "",
    "Label": "Total Multifamily Units",
    "Year": 2017
  },
  {
    "ID": "ID014",
    "Type": "Change",
    "Units": "",
    "Label": "Change in Multifamily Units",
    "Year": "since 2010"
  },
  {
    "ID": "ID015",
    "Type": "Percent",
    "Units": "",
    "Label": "Percent Renter Households",
    "Year": 2010
  },
  {
    "ID": "ID016",
    "Type": "Percent",
    "Units": "",
    "Label": "Percent Renter Households",
    "Year": 2017
  },
  {
    "ID": "ID017",
    "Type": "Change",
    "Units": "",
    "Label": "Change in Percent Renter Households",
    "Year": "since 2010"
  },
  {
    "ID": "ID018",
    "Type": "Percent",
    "Units": "",
    "Label": "Percent Owner Households",
    "Year": 2010
  },
  {
    "ID": "ID019",
    "Type": "Percent",
    "Units": "",
    "Label": "Percent Owner Households",
    "Year": 2017
  },
  {
    "ID": "ID020",
    "Type": "Percent",
    "Units": "",
    "Label": "Percent Population Under 18",
    "Year": 2010
  },
  {
    "ID": "ID021",
    "Type": "Percent",
    "Units": "",
    "Label": "Percent Population Under 18",
    "Year": 2017
  },
  {
    "ID": "ID022",
    "Type": "Percent Change",
    "Units": "",
    "Label": "Percent Change in Population Under 18",
    "Year": "since 2010"
  },
  {
    "ID": "ID023",
    "Type": "Percent",
    "Units": "",
    "Label": "Percent Population 65+",
    "Year": 2010
  },
  {
    "ID": "ID024",
    "Type": "Change",
    "Units": "",
    "Label": "Change in Population Under 18",
    "Year": "since 2010"
  },
  {
    "ID": "ID025",
    "Type": "Percent",
    "Units": "",
    "Label": "Percent Population 65+",
    "Year": 2017
  },
  {
    "ID": "ID026",
    "Type": "Change",
    "Units": "",
    "Label": "Change in Population 65+",
    "Year": "since 2010"
  },
  {
    "ID": "ID027",
    "Type": "Percent Change",
    "Units": "",
    "Label": "Percent Change in Population 65+",
    "Year": "since 2010"
  },
  {
    "ID": "ID028",
    "Type": "Per Capita",
    "Units": "dollars",
    "Label": "Per Capita Income",
    "Year": "2010*"
  },
  {
    "ID": "ID029",
    "Type": "Per Capita",
    "Units": "dollars",
    "Label": "Per Capita Income",
    "Year": 2017
  },
  {
    "ID": "ID030",
    "Type": "Percent Change",
    "Units": "dollars",
    "Label": "Percent Change in Per Capita Income",
    "Year": "since 2010"
  },
  {
    "ID": "ID031",
    "Type": "Average",
    "Units": "dollars",
    "Label": "Average Household Income",
    "Year": "2010*"
  },
  {
    "ID": "ID032",
    "Type": "Average",
    "Units": "dollars",
    "Label": "Average Household Income",
    "Year": 2017
  },
  {
    "ID": "ID033",
    "Type": "Percent Change",
    "Units": "dollars",
    "Label": "Percent Change in Mean Household Income",
    "Year": "since 2010"
  },
  {
    "ID": "ID034",
    "Type": "Average",
    "Units": "dollars",
    "Label": "Average Gross Rent",
    "Year": 2010
  },
  {
    "ID": "ID035",
    "Type": "Average",
    "Units": "dollars",
    "Label": "Average Gross Rent",
    "Year": 2017
  },
  {
    "ID": "ID036",
    "Type": "Percent Change",
    "Units": "dollars",
    "Label": "Percent Change in Average Gross Rent",
    "Year": "since 2010"
  },
  {
    "ID": "ID037",
    "Type": "Change",
    "Units": "dollars",
    "Label": "Change in Average Gross Rent",
    "Year": "since 2010"
  },
  {
    "ID": "ID038",
    "Type": "Average",
    "Units": "minutes",
    "Label": "Average Travel Time to Work",
    "Year": "2010**"
  },
  {
    "ID": "ID039",
    "Type": "Average",
    "Units": "minutes",
    "Label": "Average Travel Time to Work",
    "Year": "2017**"
  },
  {
    "ID": "ID040",
    "Type": "Change",
    "Units": "dollars",
    "Label": "Change in Per Capita Income",
    "Year": "since 2010*"
  },
  {
    "ID": "ID041",
    "Type": "Home",
    "Units": "",
    "Label": "Home Loan Denial Rate",
    "Year": 2017
  },
  {
    "ID": "ID042",
    "Type": "Percent",
    "Units": "",
    "Label": "Percent of Households without a Vehicle",
    "Year": 2010
  },
  {
    "ID": "ID043",
    "Type": "Percent",
    "Units": "",
    "Label": "Percent of Households without a Vehicle",
    "Year": 2017
  },
  {
    "ID": "ID044",
    "Type": "Change",
    "Units": "",
    "Label": "Change in Percent of Households without a Vehicle",
    "Year": "since 2010"
  },
  {
    "ID": "ID045",
    "Type": "Percent",
    "Units": "",
    "Label": "Percent of Population in Poverty",
    "Year": 2010
  },
  {
    "ID": "ID046",
    "Type": "Percent",
    "Units": "",
    "Label": "Percent of Population in Poverty",
    "Year": 2017
  },
  {
    "ID": "ID047",
    "Type": "Change",
    "Units": "",
    "Label": "Change in Percent of Population in Poverty",
    "Year": "since 2010"
  },
  {
    "ID": "ID048",
    "Type": "Percent",
    "Units": "",
    "Label": "Percent Cost Burdened Households",
    "Year": "2017***"
  },
  {
    "ID": "ID049",
    "Type": "Percent",
    "Units": "",
    "Label": "Percent Cost Burdened Renters",
    "Year": "2017***"
  },
  {
    "ID": "ID050",
    "Type": "Percent",
    "Units": "",
    "Label": "Percent Cost Burdened Owners",
    "Year": "2017***"
  },
  {
    "ID": "ID051",
    "Type": "Percent",
    "Units": "",
    "Label": "Percent Cost Burdened Households",
    "Year": "2010***"
  },
  {
    "ID": "ID052",
    "Type": "Percent",
    "Units": "",
    "Label": "Percent Cost Burdened Renters",
    "Year": "2010***"
  },
  {
    "ID": "ID053",
    "Type": "Percent",
    "Units": "",
    "Label": "Percent Cost Burdened Owners",
    "Year": "2010***"
  },
  {
    "ID": "ID054",
    "Type": "Change",
    "Units": "",
    "Label": "Change in Percent Cost Burdened Households",
    "Year": "since 2010"
  },
  {
    "ID": "ID055",
    "Type": "Change",
    "Units": "",
    "Label": "Change in Percent Cost Burdened Renters",
    "Year": "since 2010"
  },
  {
    "ID": "ID056",
    "Type": "Change",
    "Units": "",
    "Label": "Change in Percent Cost Burdened Owners",
    "Year": "since 2010"
  },
  {
    "ID": "ID057",
    "Type": "Change",
    "Units": "",
    "Label": "Change in Percent of Occupied Housing Units, Single Family Owners",
    "Year": "since 2010"
  },
  {
    "ID": "ID058",
    "Type": "Home",
    "Units": "dollars",
    "Label": "Home Sale Price Per Sq Ft",
    "Year": 2018
  },
  {
    "ID": "ID059",
    "Type": "Home",
    "Units": "dollars",
    "Label": "Home Sale Price Per Sq Ft",
    "Year": 2017
  },
  {
    "ID": "ID060",
    "Type": "Home",
    "Units": "dollars",
    "Label": "Home Sale Price Per Sq Ft",
    "Year": 2013
  },
  {
    "ID": "ID061",
    "Type": "YTY Change",
    "Units": "dollars",
    "Label": "YTY Change in Home Sale Price Per Sq Ft",
    "Year": "2017 to 2018"
  },
  {
    "ID": "ID062",
    "Type": "5-Year Change",
    "Units": "",
    "Label": "5-Year Change in Home Sale Price Per Sq Ft",
    "Year": "2013 to 2018"
  },
  {
    "ID": "ID063",
    "Type": "5-Year Percent",
    "Units": "",
    "Label": "5-Year Percent Change in Home Sale Price Per Sq Ft",
    "Year": "2013 to 2018"
  },
  {
    "ID": "ID064",
    "Type": "YTY Percent",
    "Units": "dollars",
    "Label": "YTY Percent Change in Home Sale Price Per Sq Ft",
    "Year": "2017 to 2018"
  },
  {
    "ID": "ID065",
    "Type": "Change",
    "Units": "",
    "Label": "Change in Renter Households",
    "Year": "since 2010"
  },
  {
    "ID": "ID066",
    "Type": "Change",
    "Units": "",
    "Label": "Change in Percent of Occupied Housing Units, Single Family Renters",
    "Year": "since 2010"
  },
  {
    "ID": "ID067",
    "Type": "Change",
    "Units": "",
    "Label": "Change in Owner Households",
    "Year": "since 2010"
  },
  {
    "ID": "ID068",
    "Type": "Change",
    "Units": "",
    "Label": "Change in Single Family Owners",
    "Year": "since 2010"
  },
  {
    "ID": "ID069",
    "Type": "Cost",
    "Units": "",
    "Label": "Cost Burdened Households",
    "Year": 2010
  },
  {
    "ID": "ID070",
    "Type": "Cost",
    "Units": "",
    "Label": "Cost Burdened Households",
    "Year": 2017
  },
  {
    "ID": "ID071",
    "Type": "Cost",
    "Units": "",
    "Label": "Cost Burdened Owners",
    "Year": 2010
  },
  {
    "ID": "ID072",
    "Type": "Cost",
    "Units": "",
    "Label": "Cost Burdened Owners",
    "Year": 2017
  },
  {
    "ID": "ID073",
    "Type": "Cost",
    "Units": "",
    "Label": "Cost Burdened Renters",
    "Year": 2010
  },
  {
    "ID": "ID074",
    "Type": "Cost",
    "Units": "",
    "Label": "Cost Burdened Renters",
    "Year": 2017
  },
  {
    "ID": "ID075",
    "Type": "Home",
    "Units": "",
    "Label": "Home Loan Denials",
    "Year": 2017
  },
  {
    "ID": "ID076",
    "Type": "Home",
    "Units": "",
    "Label": "Home Loans Originated",
    "Year": 2017
  },
  {
    "ID": "ID077",
    "Type": "Toal",
    "Units": "",
    "Label": "Toal Housing Units",
    "Year": 2010
  },
  {
    "ID": "ID078",
    "Type": "Total",
    "Units": "",
    "Label": "Total Housing Units",
    "Year": 2017
  },
  {
    "ID": "ID079",
    "Type": "Total",
    "Units": "",
    "Label": "Total Households without a Vehicle",
    "Year": 2017
  },
  {
    "ID": "ID080",
    "Type": "Total",
    "Units": "",
    "Label": "Total Households without a Vehicle",
    "Year": 2010
  },
  {
    "ID": "ID081",
    "Type": "Percent",
    "Units": "",
    "Label": "Percent of Occupied Housing Units, Single Family Owners",
    "Year": 2010
  },
  {
    "ID": "ID082",
    "Type": "Percent",
    "Units": "",
    "Label": "Percent of Occupied Housing Units, Single Family Renters",
    "Year": 2010
  },
  {
    "ID": "ID083",
    "Type": "Population",
    "Units": "",
    "Label": "Population 18 and Under",
    "Year": 2010
  },
  {
    "ID": "ID084",
    "Type": "Population",
    "Units": "",
    "Label": "Population 18 and Under",
    "Year": 2017
  },
  {
    "ID": "ID085",
    "Type": "Population",
    "Units": "",
    "Label": "Population 65 and Over",
    "Year": 2010
  },
  {
    "ID": "ID086",
    "Type": "Population",
    "Units": "",
    "Label": "Population 65 and Over",
    "Year": 2017
  },
  {
    "ID": "ID087",
    "Type": "Population",
    "Units": "",
    "Label": "Population in Poverty",
    "Year": 2010
  },
  {
    "ID": "ID088",
    "Type": "Population",
    "Units": "",
    "Label": "Population in Poverty",
    "Year": 2017
  },
  {
    "ID": "ID089",
    "Type": "Total",
    "Units": "",
    "Label": "Total Owner Occupied Housing Units",
    "Year": 2010
  },
  {
    "ID": "ID090",
    "Type": "Total",
    "Units": "",
    "Label": "Total Renter Occupied Housing Units",
    "Year": 2010
  },
  {
    "ID": "ID091",
    "Type": "Total",
    "Units": "",
    "Label": "Total Occupied Housing Units",
    "Year": 2010
  },
  {
    "ID": "ID092",
    "Type": "Total",
    "Units": "",
    "Label": "Total Owner Occupied Housing Units",
    "Year": 2017
  },
  {
    "ID": "ID093",
    "Type": "Total",
    "Units": "",
    "Label": "Total Renter Occupied Housing Units",
    "Year": 2017
  },
  {
    "ID": "ID094",
    "Type": "Total",
    "Units": "",
    "Label": "Total Occupied Housing Units",
    "Year": 2017
  },
  {
    "ID": "ID095",
    "Type": "Total",
    "Units": "",
    "Label": "Total Single Family Owners",
    "Year": 2010
  },
  {
    "ID": "ID096",
    "Type": "Total",
    "Units": "",
    "Label": "Total Single Family Renters",
    "Year": 2010
  },
  {
    "ID": "ID097",
    "Type": "Total",
    "Units": "",
    "Label": "Total Single Family Owners",
    "Year": 2017
  },
  {
    "ID": "ID098",
    "Type": "Total",
    "Units": "",
    "Label": "Total Single Family Renters",
    "Year": 2017
  },
  {
    "ID": "ID099",
    "Type": "Total",
    "Units": "",
    "Label": "Total Jobs",
    "Year": 2017
  },
  {
    "ID": "ID0100",
    "Type": "Total",
    "Units": "",
    "Label": "Total Multifamily Units",
    "Year": 2010
  },
  {
    "ID": "ID101",
    "Type": "Total",
    "Units": "",
    "Label": "Total Population",
    "Year": 2010
  },
  {
    "ID": "ID102",
    "Type": "Total",
    "Units": "",
    "Label": "Total Population",
    "Year": 2017
  },
  {
    "ID": "ID103",
    "Type": "Total",
    "Units": "",
    "Label": "Total Processed Home Loan Applications",
    "Year": 2017
  },
  {
    "ID": "ID104",
    "Type": "Total",
    "Units": "",
    "Label": "Total Workers",
    "Year": 2017
  },
  {
    "ID": "ID105",
    "Type": "Total",
    "Units": "",
    "Label": "Total Single Family Housing Units",
    "Year": 2010
  },
  {
    "ID": "ID106",
    "Type": "Total",
    "Units": "",
    "Label": "Total Single Family Housing Units",
    "Year": 2017
  },
  {
    "ID": "ID107",
    "Type": "Total",
    "Units": "",
    "Label": "Total Vacant Housing Units",
    "Year": 2010
  },
  {
    "ID": "ID108",
    "Type": "Total",
    "Units": "",
    "Label": "Total Vacancy Housing Units",
    "Year": 2017
  },
  {
    "ID": "ID109",
    "Type": "Workers",
    "Units": "",
    "Label": "Workers not Working from Home",
    "Year": 2010
  },
  {
    "ID": "ID110",
    "Type": "Workers",
    "Units": "",
    "Label": "Workers not Working from Home",
    "Year": 2017
  }
]